odoo/addons/product_cost_price_avco_sync/README.rst
odoo/addons/product_cost_price_avco_sync/__init__.py
odoo/addons/product_cost_price_avco_sync/__manifest__.py
odoo/addons/product_cost_price_avco_sync/i18n/es.po
odoo/addons/product_cost_price_avco_sync/i18n/it.po
odoo/addons/product_cost_price_avco_sync/i18n/product_cost_price_avco_sync.pot
odoo/addons/product_cost_price_avco_sync/i18n/pt_BR.po
odoo/addons/product_cost_price_avco_sync/models/__init__.py
odoo/addons/product_cost_price_avco_sync/models/product_product.py
odoo/addons/product_cost_price_avco_sync/models/stock_move_line.py
odoo/addons/product_cost_price_avco_sync/models/stock_picking.py
odoo/addons/product_cost_price_avco_sync/models/stock_valuation_layer.py
odoo/addons/product_cost_price_avco_sync/readme/CONTRIBUTORS.md
odoo/addons/product_cost_price_avco_sync/readme/DESCRIPTION.md
odoo/addons/product_cost_price_avco_sync/static/description/icon.png
odoo/addons/product_cost_price_avco_sync/static/description/index.html
odoo/addons/product_cost_price_avco_sync/tests/__init__.py
odoo/addons/product_cost_price_avco_sync/tests/test_product_cost_price_avco_sync.py
odoo_addon_product_cost_price_avco_sync-18.0.1.0.0.2.dist-info/METADATA
odoo_addon_product_cost_price_avco_sync-18.0.1.0.0.2.dist-info/WHEEL
odoo_addon_product_cost_price_avco_sync-18.0.1.0.0.2.dist-info/top_level.txt
odoo_addon_product_cost_price_avco_sync-18.0.1.0.0.2.dist-info/RECORD
